{
  "stores": [
    {
      "id": "shimbashi",
      "name": "新橋店",
      "address": "東京都港区新橋6-16-4 松永ビル1階",
      "phone": "03-3432-3720",
      "access": [
        "都営三田線 御成門駅より徒歩3分",
        "JR山手線 新橋駅より徒歩9分",
        "都営大江戸線 大門駅より徒歩9分"
      ]
    },
    {
      "id": "shinagawa",
      "name": "品川店",
      "address": "（要確認）",
      "phone": "03-5769-2722"
    }
  ],
  "deliveryTiers": [
    {
      "minAmount": 700,
      "label": "700円〜",
      "areas": [
        "赤坂１〜７丁目",
        "麻布十番",
        "麻布台",
        "麻布永坂町",
        "麻布狸穴町",
        "愛宕",
        "内幸町",
        "海岸１・２丁目",
        "霞ヶ関",
        "銀座",
        "芝",
        "芝浦１・２丁目",
        "芝公園",
        "芝大門",
        "新橋",
        "築地１・２・４・５丁目",
        "虎ノ門",
        "西新橋",
        "浜松町",
        "東麻布",
        "東新橋",
        "日比谷公園",
        "丸の内３丁目",
        "三田（港区）",
        "有楽町",
        "六本木"
      ]
    },
    {
      "minAmount": 1400,
      "label": "1,400円〜",
      "areas": [
        "赤坂８・９丁目",
        "明石町",
        "大手町",
        "海岸３丁目",
        "紀尾井町",
        "皇居外苑",
        "港南",
        "芝浦３・４丁目",
        "白金１・２丁目",
        "白金台１・２丁目",
        "新富",
        "高輪",
        "築地３・６・７丁目",
        "永田町",
        "西麻布１・３丁目",
        "丸の内１・２丁目",
        "南青山１丁目",
        "南麻布１・２・３・５丁目",
        "元赤坂",
        "元麻布"
      ]
    },
    {
      "minAmount": 2000,
      "label": "2,000円〜",
      "areas": [
        "大崎１丁目",
        "勝どき",
        "北品川",
        "白金３〜５丁目",
        "西麻布２・４丁目",
        "西五反田１・２丁目",
        "隼町",
        "東五反田",
        "東品川１〜３丁目",
        "平河町",
        "南麻布４丁目",
        "南品川１・２丁目"
      ]
    },
    {
      "minAmount": 2500,
      "label": "2,500円〜",
      "areas": [
        "青海１・２丁目",
        "有明１丁目",
        "上大崎１丁目",
        "白金６丁目",
        "白金台３〜５丁目",
        "台場",
        "月島",
        "南青山２丁目"
      ]
    },
    {
      "minAmount": 3000,
      "label": "3,000円〜",
      "areas": [
        "青海３・４丁目",
        "麹町",
        "西五反田７・８丁目",
        "南品川４丁目"
      ]
    }
  ],
  "outsideArea": {
    "within23ku": { "minAmount": 15000, "description": "23区内" },
    "suburbs": { "minAmount": 20000, "description": "都内近郊" },
    "requiresReservation": true,
    "reservationDeadline": "前日まで"
  },
  "businessHours": {
    "phoneReception": {
      "weekday": "9:00〜14:00、16:30〜21:00",
      "saturday": "9:00〜14:00、16:30〜20:00",
      "sunday": "予約のみ対応"
    }
  },
  "paymentMethods": [
    { "id": "cash", "name": "現金", "available": true },
    { "id": "qr", "name": "QRコード決済", "available": true }
  ],
  "_meta": {
    "lastUpdated": "2026-02-27",
    "source": "配達エリア料金表（2026年2月更新）"
  }
}
