{
  "month": "2月",
  "year": "2026",
  "menuName": "桜桃",
  "menuReading": "サクランボ",
  "price": 700,
  "schedule": [
    {
      "day": "月",
      "items": [
        "チーズ入りチキンカツ",
        "甘ピリ鶏ごぼう",
        "みぞれ揚げだし豆腐"
      ]
    },
    {
      "day": "火",
      "items": [
        "和風蓮根ソースハンバーグ",
        "コーンフライ",
        "白菜のガーリック炒め"
      ]
    },
    {
      "day": "水",
      "items": [
        "クリスピーチキン",
        "白身魚フライ",
        "桜海老とキャベツのペペロンチーノ"
      ]
    },
    {
      "day": "木",
      "items": [
        "キャベツメンチカツ",
        "梅風味の白菜サラダ",
        "蒟蒻炒め"
      ]
    },
    {
      "day": "金",
      "items": [
        "豚肉と玉ねぎの生姜焼き",
        "サラダ",
        "切干大根と紅生姜のかき揚げ（おろし添え）"
      ]
    },
    {
      "day": "土",
      "items": [],
      "note": "当日、お電話にてご確認ください。"
    }
  ],
  "_meta": {
    "lastUpdated": "2026-02-24",
    "note": "毎月更新"
  }
}
